morphine/__init__.py
morphine/cli.py
morphine/colors.py
morphine/trace_formatter.py
morphine/trace_shell.py
morphine_tracer-0.1.0.dist-info/LICENSE
morphine_tracer-0.1.0.dist-info/METADATA
morphine_tracer-0.1.0.dist-info/WHEEL
morphine_tracer-0.1.0.dist-info/entry_points.txt
morphine_tracer-0.1.0.dist-info/top_level.txt
morphine_tracer-0.1.0.dist-info/RECORD
