Metadata-Version: 2.1
Name: morphine-tracer
Version: 0.1.0
Summary: Simple Prolog trace formatter
Home-page: https://github.com/skalermo/morphine
Author: Roman Moskalenko
Author-email: skalermo@gmail.com
License: MIT license
Keywords: morphine
Platform: UNKNOWN
Classifier: Development Status :: 2 - Pre-Alpha
Classifier: Intended Audience :: Developers
Classifier: License :: OSI Approved :: MIT License
Classifier: Natural Language :: English
Classifier: Programming Language :: Python :: 3
Classifier: Programming Language :: Python :: 3.5
Classifier: Programming Language :: Python :: 3.6
Classifier: Programming Language :: Python :: 3.7
Classifier: Programming Language :: Python :: 3.8
Requires-Python: >=3.5
